{
    "metadata": {
        "uuid": "32dc45c8-e9fb-487d-b8a8-a5591b899acc",
        "date_created": "2025-05-23T20:48:09.333455",
        "task": "Hallucinate Tree",
        "time_taken": "0:00:21.272869"
    },
    "tree": {
        "step": "Robotic Assembly",
        "children": [
            {
                "step": "```json\n[\n  {\n    \"step\": \"Define Assembly Requirements\"\n  },\n  {\n    \"step\": \"Design Robot Path and Movements\"\n  },\n  {\n    \"step\": \"Select and Configure Robotic Arm\"\n  },\n  {\n    \"step\": \"Secure Components to Workpiece\"\n  },\n  {\n    \"step\": \"Robot Performs Assembly Operations\"\n  },\n  {\n    \"step\": \"Quality Check and Verification\"\n  },\n  {\n    \"step\": \"Document Assembly Process\"\n  }\n]\n```",
                "children": []
            }
        ],
        "uuid": "32dc45c8-e9fb-487d-b8a8-a5591b899acc"
    }
}