{
    "metadata": {
        "uuid": "a9a0b48e-4b0e-4192-8849-52a95c9762a1",
        "date_created": "2025-05-23T20:19:30.599880",
        "task": "Hallucinate Tree",
        "time_taken": "0:00:08.989102"
    },
    "tree": {
        "step": "Robotic Assembly",
        "children": [
            {
                "step": "Define Assembly Requirements",
                "children": [
                    {
                        "step": "Identify Stakeholders"
                    },
                    {
                        "step": "Determine Required Documentation"
                    },
                    {
                        "step": "Establish Quality Standards"
                    },
                    {
                        "step": "Define Acceptance Criteria"
                    },
                    {
                        "step": "Document Assembly Procedures"
                    },
                    {
                        "step": "Verify Assembly Processes"
                    }
                ]
            },
            {
                "step": "Design Robotic System",
                "children": [
                    {
                        "step": "Define System Requirements"
                    },
                    {
                        "step": "Specify Functional Requirements"
                    },
                    {
                        "step": "Determine Operational Environment"
                    },
                    {
                        "step": "Select Robot Platform"
                    },
                    {
                        "step": "Design Robot Hardware"
                    },
                    {
                        "step": "Develop Robot Software"
                    },
                    {
                        "step": "Test and Integrate System"
                    }
                ]
            },
            {
                "step": "Select and Configure Robot",
                "children": [
                    {
                        "step": "Define Robot Requirements"
                    },
                    {
                        "step": "Research and Identify Suitable Robots"
                    },
                    {
                        "step": "Evaluate Robot Specifications"
                    },
                    {
                        "step": "Select Preferred Robot Model"
                    },
                    {
                        "step": "Configure Robot Software"
                    },
                    {
                        "step": "Adjust Robot Settings"
                    },
                    {
                        "step": "Test Robot Functionality"
                    }
                ]
            },
            {
                "step": "Develop Robotic Program",
                "children": [
                    {
                        "step": "Define Program Requirements"
                    },
                    {
                        "step": "Design Robot Architecture"
                    },
                    {
                        "step": "Develop Control Logic"
                    },
                    {
                        "step": "Implement Sensor Integration"
                    },
                    {
                        "step": "Test and Debug Program"
                    },
                    {
                        "step": "Optimize Program Performance"
                    }
                ]
            },
            {
                "step": "Test and Debug Program",
                "children": [
                    {
                        "step": "Understand Program Requirements"
                    },
                    {
                        "step": "Create Test Cases"
                    },
                    {
                        "step": "Execute Test Cases"
                    },
                    {
                        "step": "Analyze Test Results"
                    },
                    {
                        "step": "Identify and Report Bugs"
                    },
                    {
                        "step": "Debug the Code"
                    },
                    {
                        "step": "Retest After Debugging"
                    }
                ]
            },
            {
                "step": "Integrate Robot into Assembly Line",
                "children": [
                    {
                        "step": "Assess Existing Assembly Line"
                    },
                    {
                        "step": "Determine Robot Capabilities and Specifications"
                    },
                    {
                        "step": "Design Robot Integration Points"
                    },
                    {
                        "step": "Modify Assembly Line for Robot Integration"
                    },
                    {
                        "step": "Program Robot for Specific Tasks"
                    },
                    {
                        "step": "Test Robot Integration and Performance"
                    },
                    {
                        "step": "Train Personnel on Robot Operation and Maintenance"
                    }
                ]
            },
            {
                "step": "Monitor and Maintain Robot Performance",
                "children": [
                    {
                        "step": "Establish Baseline Performance Metrics"
                    },
                    {
                        "step": "Collect Performance Data Regularly"
                    },
                    {
                        "step": "Analyze Performance Data for Anomalies"
                    },
                    {
                        "step": "Identify Root Causes of Performance Issues"
                    },
                    {
                        "step": "Implement Corrective Actions"
                    },
                    {
                        "step": "Test and Validate Corrective Actions"
                    },
                    {
                        "step": "Document Changes and Adjust Baseline"
                    }
                ]
            }
        ],
        "uuid": "a9a0b48e-4b0e-4192-8849-52a95c9762a1"
    }
}